papyllon/__init__.py
papyllon/constructors.py
papyllon/graphviz_templates.py
papyllon/viz.py
papyllon-0.0.3.dist-info/LICENSE
papyllon-0.0.3.dist-info/METADATA
papyllon-0.0.3.dist-info/WHEEL
papyllon-0.0.3.dist-info/top_level.txt
papyllon-0.0.3.dist-info/RECORD
