Metadata-Version: 2.1
Name: papyllon
Version: 0.0.3
Summary: Yet another package to work with graphs and networks
Home-page: https://github.com/thorwhalen/newut/tree/master/papyllon
Author: Thor Whalen
License: mit
Platform: any
License-File: LICENSE
